AUTHOR.txt
CHANGES.txt
LICENSE.txt
README.txt
TODO.txt
bootstrap.py
buildout.cfg
setup.py
src/z3c/__init__.py
src/z3c.formjs.egg-info/PKG-INFO
src/z3c.formjs.egg-info/SOURCES.txt
src/z3c.formjs.egg-info/dependency_links.txt
src/z3c.formjs.egg-info/namespace_packages.txt
src/z3c.formjs.egg-info/not-zip-safe
src/z3c.formjs.egg-info/requires.txt
src/z3c.formjs.egg-info/top_level.txt
src/z3c/formjs/README.txt
src/z3c/formjs/SETUP.cfg
src/z3c/formjs/__init__.py
src/z3c/formjs/ajax.py
src/z3c/formjs/ajax.txt
src/z3c/formjs/configure.zcml
src/z3c/formjs/index.txt
src/z3c/formjs/interfaces.py
src/z3c/formjs/jquery-switch.js
src/z3c/formjs/jqueryrenderer.py
src/z3c/formjs/jqueryrenderer.txt
src/z3c/formjs/jqueryrenderer.zcml
src/z3c/formjs/jsaction.py
src/z3c/formjs/jsaction.txt
src/z3c/formjs/jsclientevent.py
src/z3c/formjs/jsclientevent.txt
src/z3c/formjs/jsevent.py
src/z3c/formjs/jsevent.txt
src/z3c/formjs/jsfunction.py
src/z3c/formjs/jsfunction.txt
src/z3c/formjs/jsswitch.py
src/z3c/formjs/jsswitch.txt
src/z3c/formjs/jsvalidator.py
src/z3c/formjs/jsvalidator.txt
src/z3c/formjs/jswidget.txt
src/z3c/formjs/testing.py
src/z3c/formjs/z3c.formjs-configure.zcml
src/z3c/formjs/tests/__init__.py
src/z3c/formjs/tests/buttons_form.pt
src/z3c/formjs/tests/simple_edit.pt
src/z3c/formjs/tests/test_doc.py